usgsdownload
