Metadata-Version: 1.1
Name: USGSDownload
Version: 0.6
Summary: USGS Download for download landsat data
Home-page: https://github.com/lucaslamounier/USGSDownload/
Author: Lucas Lamounier
Author-email: lucasls.oas@gmail.com
License: MIT
Download-URL: https://github.com/lucaslamounier/USGSDownload/tarball/0.6
Platform: UNKNOWN
